{
    "header": {
        "link1": "Главная",
        "link2": "О нас",
        "link3": "Наши бренды",
        "link4": "Контакты"
    },
    "hero": {
        "title1": "СОЗДАЙТЕ СВОЙ СОБСТВЕННЫЙ АРОМАТ",
        "text1": "Наши опытные парфюмеры создадут по-настоящему уникальный аромат, используя лучшие ингредиенты и современные технологии",
        "btn1": "СВЯЗАТЬСЯ С НАМИ",
        "title2": "ОТКРОЙТЕ СВОЙ УНИКАЛЬНЫЙ АРОМАТ",
        "text2": "Окунитесь в наши эксклюзивные коллекции, каждая из которых рассказывает историю элегантности и шарма",
        "btn2": "ОСТАВИТЬ ЗАЯВКУ",
        "title3": "ЭКСКЛЮЗИВНЫЕ КОЛЛЕКЦИИ",
        "text3": "Почувствуйте искусство парфюмерии с нашей эксклюзивной линией роскошных ароматов, созданных до совершенства",
        "btn3": "СМОТРЕТЬ"
    }
}